{"აბაშა":{"download":38.8,"download_min":1.8,"download_max":122.4,"upload":10.5,"upload_min":0.3,"upload_max":47.5,"ping":24,"ping_min":16,"ping_max":37,"tests":49,"devices":20,"locations":18},"ადიგენი":{"download":26.6,"download_min":2.6,"download_max":56.3,"upload":10.2,"upload_min":1.2,"upload_max":27.8,"ping":33,"ping_min":15,"ping_max":176,"tests":15,"devices":13,"locations":12},"ამბროლაური":{"download":32.0,"download_min":2.0,"download_max":62.9,"upload":10.1,"upload_min":0.3,"upload_max":22.7,"ping":28,"ping_min":17,"ping_max":49,"tests":51,"devices":24,"locations":18},"ასპინძა":{"download":45.7,"download_min":0.2,"download_max":114.2,"upload":8.0,"upload_min":0.0,"upload_max":25.1,"ping":24,"ping_min":16,"ping_max":43,"tests":44,"devices":15,"locations":15},"ახალქალაქი":{"download":33.1,"download_min":0.6,"download_max":165.5,"upload":10.6,"upload_min":0.6,"upload_max":43.9,"ping":24,"ping_min":10,"ping_max":70,"tests":108,"devices":67,"locations":55},"ახალციხე":{"download":22.6,"download_min":2.0,"download_max":52.6,"upload":12.3,"upload_min":0.2,"upload_max":60.1,"ping":35,"ping_min":13,"ping_max":146,"tests":40,"devices":25,"locations":19},"ახმეტა":{"download":27.7,"download_min":1.2,"download_max":153.5,"upload":9.4,"upload_min":0.9,"upload_max":35.2,"ping":31,"ping_min":12,"ping_max":180,"tests":52,"devices":31,"locations":25},"ბათუმი":{"download":40.4,"download_min":0.8,"download_max":154.4,"upload":14.4,"upload_min":0.1,"upload_max":78.7,"ping":26,"ping_min":15,"ping_max":199,"tests":1114,"devices":561,"locations":115},"ბაღდათი":{"download":29.5,"download_min":3.9,"download_max":73.3,"upload":7.8,"upload_min":1.0,"upload_max":28.4,"ping":20,"ping_min":15,"ping_max":37,"tests":25,"devices":12,"locations":11},"ბოლნისი":{"download":24.7,"download_min":0.3,"download_max":91.9,"upload":8.6,"upload_min":0.2,"upload_max":37.8,"ping":25,"ping_min":13,"ping_max":128,"tests":55,"devices":29,"locations":27},"ბორჯომი":{"download":56.5,"download_min":2.7,"download_max":124.9,"upload":17.4,"upload_min":1.1,"upload_max":44.3,"ping":19,"ping_min":14,"ping_max":32,"tests":24,"devices":23,"locations":18},"გაგრა":{"download":24.8,"download_min":4.1,"download_max":95.8,"upload":12.9,"upload_min":0.4,"upload_max":55.4,"ping":31,"ping_min":10,"ping_max":105,"tests":228,"devices":154,"locations":67},"გარდაბანი":{"download":27.5,"download_min":1.3,"download_max":116.6,"upload":9.2,"upload_min":0.1,"upload_max":32.1,"ping":22,"ping_min":5,"ping_max":83,"tests":181,"devices":66,"locations":63},"გორი":{"download":36.9,"download_min":0.2,"download_max":138.5,"upload":13.9,"upload_min":0.0,"upload_max":62.4,"ping":25,"ping_min":12,"ping_max":134,"tests":316,"devices":140,"locations":100},"გუდაუთა":{"download":17.9,"download_min":4.3,"download_max":44.2,"upload":13.4,"upload_min":1.1,"upload_max":30.3,"ping":18,"ping_min":11,"ping_max":33,"tests":33,"devices":25,"locations":20},"გულრიფში":{"download":113.5,"download_min":113.5,"download_max":113.5,"upload":16.0,"upload_min":16.0,"upload_max":16.0,"ping":82,"ping_min":82,"ping_max":82,"tests":1,"devices":1,"locations":1},"გურჯაანი":{"download":29.4,"download_min":0.3,"download_max":137.3,"upload":7.5,"upload_min":0.0,"upload_max":23.1,"ping":25,"ping_min":13,"ping_max":121,"tests":99,"devices":39,"locations":36},"დედოფლისწყარო":{"download":44.4,"download_min":2.8,"download_max":117.9,"upload":11.9,"upload_min":0.4,"upload_max":36.9,"ping":43,"ping_min":13,"ping_max":339,"tests":64,"devices":24,"locations":18},"დმანისი":{"download":28.4,"download_min":3.8,"download_max":67.2,"upload":9.1,"upload_min":2.0,"upload_max":23.9,"ping":21,"ping_min":15,"ping_max":25,"tests":15,"devices":8,"locations":7},"დუშეთი":{"download":35.8,"download_min":1.1,"download_max":142.8,"upload":11.8,"upload_min":0.4,"upload_max":77.2,"ping":24,"ping_min":11,"ping_max":140,"tests":151,"devices":65,"locations":59},"ვანი":{"download":15.2,"download_min":0.0,"download_max":29.5,"upload":4.5,"upload_min":0.3,"upload_max":12.7,"ping":28,"ping_min":10,"ping_max":51,"tests":18,"devices":10,"locations":6},"ზესტაფონი":{"download":20.4,"download_min":0.4,"download_max":69.1,"upload":6.2,"upload_min":0.1,"upload_max":40.2,"ping":32,"ping_min":16,"ping_max":201,"tests":48,"devices":32,"locations":26},"ზუგდიდი":{"download":39.1,"download_min":0.6,"download_max":124.0,"upload":13.0,"upload_min":0.2,"upload_max":49.3,"ping":27,"ping_min":16,"ping_max":129,"tests":167,"devices":91,"locations":67},"თბილისი":{"download":40.2,"download_min":0.4,"download_max":173.0,"upload":16.2,"upload_min":0.0,"upload_max":59.2,"ping":22,"ping_min":2,"ping_max":246,"tests":5137,"devices":2477,"locations":613},"თეთრი წყაროს":{"download":43.5,"download_min":2.1,"download_max":155.8,"upload":13.4,"upload_min":0.3,"upload_max":50.6,"ping":24,"ping_min":11,"ping_max":159,"tests":38,"devices":28,"locations":23},"თელავი":{"download":30.5,"download_min":0.3,"download_max":87.6,"upload":10.5,"upload_min":0.4,"upload_max":49.0,"ping":21,"ping_min":13,"ping_max":48,"tests":112,"devices":63,"locations":47},"თერჯოლა":{"download":32.7,"download_min":1.2,"download_max":103.6,"upload":8.3,"upload_min":0.3,"upload_max":37.9,"ping":28,"ping_min":14,"ping_max":155,"tests":62,"devices":27,"locations":25},"თიანეთი":{"download":36.2,"download_min":4.1,"download_max":95.9,"upload":2.5,"upload_min":0.0,"upload_max":5.9,"ping":32,"ping_min":14,"ping_max":101,"tests":11,"devices":10,"locations":10},"კასპი":{"download":30.4,"download_min":0.5,"download_max":118.0,"upload":11.0,"upload_min":0.2,"upload_max":47.4,"ping":31,"ping_min":5,"ping_max":423,"tests":107,"devices":46,"locations":40},"ლაგოდეხი":{"download":21.4,"download_min":1.0,"download_max":82.4,"upload":8.3,"upload_min":0.2,"upload_max":38.3,"ping":64,"ping_min":15,"ping_max":347,"tests":34,"devices":22,"locations":22},"ლანჩხუთი":{"download":31.8,"download_min":2.5,"download_max":74.4,"upload":13.0,"upload_min":0.3,"upload_max":42.9,"ping":26,"ping_min":18,"ping_max":43,"tests":35,"devices":26,"locations":23},"ლენტეხი":{"download":2.0,"download_min":2.0,"download_max":2.0,"upload":3.5,"upload_min":3.5,"upload_max":3.5,"ping":40,"ping_min":40,"ping_max":40,"tests":2,"devices":1,"locations":1},"მარნეული":{"download":24.3,"download_min":0.3,"download_max":90.3,"upload":10.3,"upload_min":0.2,"upload_max":69.4,"ping":28,"ping_min":12,"ping_max":205,"tests":104,"devices":62,"locations":44},"მარტვილი":{"download":32.3,"download_min":0.9,"download_max":111.0,"upload":9.5,"upload_min":0.4,"upload_max":41.5,"ping":62,"ping_min":17,"ping_max":465,"tests":123,"devices":48,"locations":43},"მესტია":{"download":23.3,"download_min":1.2,"download_max":100.2,"upload":8.6,"upload_min":0.9,"upload_max":31.3,"ping":92,"ping_min":19,"ping_max":403,"tests":53,"devices":26,"locations":21},"მცხეთა":{"download":25.8,"download_min":0.1,"download_max":119.6,"upload":10.5,"upload_min":0.1,"upload_max":64.2,"ping":25,"ping_min":11,"ping_max":88,"tests":148,"devices":96,"locations":84},"ნინოწმინდა":{"download":21.9,"download_min":0.2,"download_max":77.8,"upload":9.1,"upload_min":0.3,"upload_max":38.6,"ping":41,"ping_min":13,"ping_max":267,"tests":43,"devices":33,"locations":27},"ოზურგეთი":{"download":31.4,"download_min":0.2,"download_max":146.7,"upload":10.3,"upload_min":0.1,"upload_max":46.7,"ping":26,"ping_min":16,"ping_max":79,"tests":82,"devices":60,"locations":52},"ონი":{"download":22.0,"download_min":6.1,"download_max":39.0,"upload":11.6,"upload_min":3.1,"upload_max":15.3,"ping":21,"ping_min":17,"ping_max":27,"tests":13,"devices":5,"locations":5},"რუსთავი":{"download":35.8,"download_min":2.6,"download_max":131.2,"upload":12.9,"upload_min":1.2,"upload_max":49.9,"ping":20,"ping_min":8,"ping_max":36,"tests":133,"devices":85,"locations":43},"საგარეჯო":{"download":28.4,"download_min":0.4,"download_max":112.1,"upload":9.0,"upload_min":0.1,"upload_max":45.2,"ping":29,"ping_min":4,"ping_max":216,"tests":38,"devices":27,"locations":25},"სამტრედია":{"download":27.8,"download_min":1.5,"download_max":78.3,"upload":9.8,"upload_min":0.4,"upload_max":59.2,"ping":30,"ping_min":15,"ping_max":113,"tests":86,"devices":45,"locations":40},"საჩხერე":{"download":23.3,"download_min":0.8,"download_max":66.8,"upload":9.1,"upload_min":0.0,"upload_max":38.5,"ping":28,"ping_min":16,"ping_max":169,"tests":95,"devices":35,"locations":32},"სენაკი":{"download":30.2,"download_min":1.1,"download_max":75.3,"upload":10.2,"upload_min":0.1,"upload_max":32.7,"ping":31,"ping_min":15,"ping_max":173,"tests":57,"devices":27,"locations":21},"სიღნაღი":{"download":27.2,"download_min":0.2,"download_max":93.0,"upload":8.1,"upload_min":0.4,"upload_max":46.7,"ping":54,"ping_min":14,"ping_max":342,"tests":41,"devices":24,"locations":20},"სოხუმი":{"download":23.4,"download_min":3.9,"download_max":90.2,"upload":13.6,"upload_min":0.1,"upload_max":43.5,"ping":19,"ping_min":6,"ping_max":44,"tests":95,"devices":68,"locations":49},"ტყიბული":{"download":30.8,"download_min":4.3,"download_max":82.9,"upload":10.5,"upload_min":1.0,"upload_max":21.1,"ping":20,"ping_min":16,"ping_max":26,"tests":4,"devices":4,"locations":4},"ფოთი":{"download":54.8,"download_min":1.4,"download_max":169.1,"upload":18.2,"upload_min":1.1,"upload_max":65.1,"ping":37,"ping_min":16,"ping_max":318,"tests":92,"devices":43,"locations":35},"ქარელი":{"download":37.3,"download_min":0.9,"download_max":152.9,"upload":15.8,"upload_min":0.3,"upload_max":51.7,"ping":21,"ping_min":12,"ping_max":33,"tests":53,"devices":33,"locations":30},"ქედა":{"download":39.2,"download_min":1.1,"download_max":116.3,"upload":10.3,"upload_min":0.6,"upload_max":32.6,"ping":31,"ping_min":15,"ping_max":168,"tests":26,"devices":22,"locations":20},"ქობულეთი":{"download":36.7,"download_min":0.2,"download_max":200.2,"upload":9.4,"upload_min":0.1,"upload_max":35.1,"ping":27,"ping_min":16,"ping_max":251,"tests":162,"devices":96,"locations":74},"ქუთაისი":{"download":34.1,"download_min":0.1,"download_max":128.0,"upload":12.2,"upload_min":0.6,"upload_max":47.5,"ping":26,"ping_min":13,"ping_max":207,"tests":199,"devices":127,"locations":72},"ყაზბეგი":{"download":53.8,"download_min":0.4,"download_max":391.2,"upload":21.1,"upload_min":0.3,"upload_max":62.9,"ping":33,"ping_min":12,"ping_max":169,"tests":113,"devices":49,"locations":39},"ყვარელი":{"download":43.9,"download_min":3.2,"download_max":90.8,"upload":8.1,"upload_min":0.5,"upload_max":17.6,"ping":40,"ping_min":16,"ping_max":167,"tests":14,"devices":10,"locations":9},"შუახევი":{"download":23.9,"download_min":0.2,"download_max":64.7,"upload":8.5,"upload_min":0.0,"upload_max":38.1,"ping":29,"ping_min":17,"ping_max":58,"tests":24,"devices":17,"locations":17},"ჩოხატაური":{"download":12.9,"download_min":0.3,"download_max":41.4,"upload":5.1,"upload_min":0.1,"upload_max":14.1,"ping":31,"ping_min":16,"ping_max":84,"tests":27,"devices":23,"locations":21},"ჩხოროწყუ":{"download":33.8,"download_min":0.8,"download_max":92.5,"upload":15.7,"upload_min":0.3,"upload_max":59.6,"ping":59,"ping_min":18,"ping_max":181,"tests":30,"devices":19,"locations":16},"ცაგერი":{"download":29.4,"download_min":1.9,"download_max":83.0,"upload":9.4,"upload_min":1.6,"upload_max":23.5,"ping":24,"ping_min":16,"ping_max":46,"tests":89,"devices":16,"locations":13},"წალენჯიხა":{"download":41.3,"download_min":5.3,"download_max":113.5,"upload":15.6,"upload_min":1.5,"upload_max":54.5,"ping":26,"ping_min":18,"ping_max":47,"tests":33,"devices":16,"locations":14},"წალკა":{"download":41.9,"download_min":5.4,"download_max":107.0,"upload":19.0,"upload_min":0.7,"upload_max":61.9,"ping":22,"ping_min":15,"ping_max":47,"tests":11,"devices":10,"locations":10},"წყალტუბო":{"download":27.9,"download_min":0.5,"download_max":118.6,"upload":11.0,"upload_min":0.1,"upload_max":59.3,"ping":31,"ping_min":15,"ping_max":150,"tests":50,"devices":35,"locations":33},"ჭიათურა":{"download":14.3,"download_min":1.0,"download_max":51.0,"upload":4.5,"upload_min":0.1,"upload_max":18.3,"ping":44,"ping_min":14,"ping_max":175,"tests":27,"devices":13,"locations":12},"ხარაგაული":{"download":38.5,"download_min":4.2,"download_max":101.1,"upload":13.0,"upload_min":0.2,"upload_max":36.9,"ping":21,"ping_min":16,"ping_max":41,"tests":31,"devices":21,"locations":20},"ხაშური":{"download":35.9,"download_min":1.8,"download_max":131.6,"upload":11.1,"upload_min":0.1,"upload_max":60.1,"ping":23,"ping_min":11,"ping_max":83,"tests":61,"devices":41,"locations":34},"ხელვაჩაური":{"download":27.2,"download_min":0.3,"download_max":137.5,"upload":10.6,"upload_min":0.2,"upload_max":51.9,"ping":25,"ping_min":15,"ping_max":69,"tests":165,"devices":68,"locations":56},"ხობი":{"download":35.7,"download_min":1.7,"download_max":173.2,"upload":6.1,"upload_min":0.0,"upload_max":23.3,"ping":26,"ping_min":17,"ping_max":56,"tests":74,"devices":32,"locations":29},"ხონი":{"download":13.2,"download_min":0.6,"download_max":35.2,"upload":6.9,"upload_min":0.1,"upload_max":28.8,"ping":51,"ping_min":17,"ping_max":285,"tests":17,"devices":14,"locations":11},"ხულო":{"download":33.1,"download_min":4.6,"download_max":106.8,"upload":11.5,"upload_min":0.5,"upload_max":42.6,"ping":40,"ping_min":18,"ping_max":171,"tests":26,"devices":17,"locations":15}}